SsdbShujukuShiyongshouce/README.md
SsdbShujukuShiyongshouce/__init__.py
SsdbShujukuShiyongshouce/__main__.py
SsdbShujukuShiyongshouce/file.epub
SsdbShujukuShiyongshouce/index.html
SsdbShujukuShiyongshouce/css/__init__.py
SsdbShujukuShiyongshouce/css/annotations.css
SsdbShujukuShiyongshouce/css/main.css
SsdbShujukuShiyongshouce/css/normalize.css
SsdbShujukuShiyongshouce/css/popup.css
SsdbShujukuShiyongshouce/font/__init__.py
SsdbShujukuShiyongshouce/font/fontello.eot
SsdbShujukuShiyongshouce/font/fontello.svg
SsdbShujukuShiyongshouce/font/fontello.ttf
SsdbShujukuShiyongshouce/font/fontello.woff
SsdbShujukuShiyongshouce/img/__init__.py
SsdbShujukuShiyongshouce/img/annotator-glyph-sprite.png
SsdbShujukuShiyongshouce/img/annotator-icon-sprite.png
SsdbShujukuShiyongshouce/img/apple-touch-icon.png
SsdbShujukuShiyongshouce/img/cancelfullscreen.png
SsdbShujukuShiyongshouce/img/close.png
SsdbShujukuShiyongshouce/img/fullscreen.png
SsdbShujukuShiyongshouce/img/loader.gif
SsdbShujukuShiyongshouce/img/menu-icon.png
SsdbShujukuShiyongshouce/img/save.png
SsdbShujukuShiyongshouce/img/saved.png
SsdbShujukuShiyongshouce/img/settings-s.png
SsdbShujukuShiyongshouce/img/settings.png
SsdbShujukuShiyongshouce/img/star.png
SsdbShujukuShiyongshouce/js/__init__.py
SsdbShujukuShiyongshouce/js/epub.js
SsdbShujukuShiyongshouce/js/epub.min.js
SsdbShujukuShiyongshouce/js/epub.min.map
SsdbShujukuShiyongshouce/js/hooks.min.js
SsdbShujukuShiyongshouce/js/hooks.min.map
SsdbShujukuShiyongshouce/js/reader.js
SsdbShujukuShiyongshouce/js/reader.js.map
SsdbShujukuShiyongshouce/js/reader.min.js
SsdbShujukuShiyongshouce/js/reader.min.map
SsdbShujukuShiyongshouce/js/hooks/__init__.py
SsdbShujukuShiyongshouce/js/hooks/extensions/__init__.py
SsdbShujukuShiyongshouce/js/hooks/extensions/highlight.js
SsdbShujukuShiyongshouce/js/libs/__init__.py
SsdbShujukuShiyongshouce/js/libs/jquery.min.js
SsdbShujukuShiyongshouce/js/libs/localforage.min.js
SsdbShujukuShiyongshouce/js/libs/screenfull.js
ssdb_shujuku_shiyongshouce-2024.3.2.0.dist-info/METADATA
ssdb_shujuku_shiyongshouce-2024.3.2.0.dist-info/WHEEL
ssdb_shujuku_shiyongshouce-2024.3.2.0.dist-info/entry_points.txt
ssdb_shujuku_shiyongshouce-2024.3.2.0.dist-info/top_level.txt
ssdb_shujuku_shiyongshouce-2024.3.2.0.dist-info/RECORD
